metadata_magic/__init__.py
metadata_magic/config.py
metadata_magic/error.py
metadata_magic/file_tools.py
metadata_magic/meta_finder.py
metadata_magic/meta_reader.py
metadata_magic/rename.py
metadata_magic/sort.py
metadata_magic/archive/__init__.py
metadata_magic/archive/archive.py
metadata_magic/archive/bulk_archive.py
metadata_magic/archive/comic_archive.py
metadata_magic/archive/comic_xml.py
metadata_magic/archive/epub.py
metadata_magic/archive/mkv.py
metadata_magic/archive/series.py
metadata_magic/archive/update.py
metadata_magic/archive/xhtml_formatting.py
metadata_magic/config_files/__init__.py
metadata_magic/config_files/config.json
metadata_magic/test/__init__.py
metadata_magic/test/test_config.py
metadata_magic/test/test_error.py
metadata_magic/test/test_file_tools.py
metadata_magic/test/test_meta_finder.py
metadata_magic/test/test_meta_reader.py
metadata_magic/test/test_rename.py
metadata_magic/test/test_sort.py
metadata_magic/test/archive/__init__.py
metadata_magic/test/archive/test_archive.py
metadata_magic/test/archive/test_bulk_archive.py
metadata_magic/test/archive/test_comic_archive.py
metadata_magic/test/archive/test_comic_xml.py
metadata_magic/test/archive/test_epub.py
metadata_magic/test/archive/test_mkv.py
metadata_magic/test/archive/test_series.py
metadata_magic/test/archive/test_update.py
metadata_magic/test/archive/test_xhtml_formatting.py
metadata_magic-0.14.2.dist-info/licenses/LICENSE
metadata_magic-0.14.2.dist-info/METADATA
metadata_magic-0.14.2.dist-info/WHEEL
metadata_magic-0.14.2.dist-info/entry_points.txt
metadata_magic-0.14.2.dist-info/top_level.txt
metadata_magic-0.14.2.dist-info/RECORD
