Metadata-Version: 2.4
Name: Metadata-Magic
Version: 0.14.2
Summary: Utility for managing metadata.
Home-page: https://github.com/Drakovek/MetadataMagic
Author: Drakovek
Author-email: DrakovekMail@gmail.com
Classifier: Programming Language :: Python :: 3
Classifier: License :: OSI Approved :: GNU General Public License v3 (GPLv3)
Classifier: Operating System :: OS Independent
Requires-Python: >=3.7
License-File: LICENSE
Requires-Dist: CoverGenerator>=0.2.1
Requires-Dist: html5lib>=1.1
Requires-Dist: HTML-String-Tools>=0.4.2
Requires-Dist: pillow>=8.0.0
Requires-Dist: Python-Print-Tools>=0.2.2
Requires-Dist: python-ffmpeg>=2.0.0
Requires-Dist: tqdm>=4.64.1
Dynamic: author
Dynamic: author-email
Dynamic: classifier
Dynamic: description
Dynamic: description-content-type
Dynamic: home-page
Dynamic: license-file
Dynamic: requires-dist
Dynamic: requires-python
Dynamic: summary
